mapgraph-0.2.9.dist-info/METADATA
mapgraph-0.2.9.dist-info/WHEEL
mapgraph-0.2.9.dist-info/entry_points.txt
mapgraph-0.2.9.dist-info/licenses/LICENSE
mapgraph/__init__.py
mapgraph/config/__init__.py
mapgraph/context.py
mapgraph/globals.py
mapgraph/instance_of.py
mapgraph/lifecycle/__init__.py
mapgraph/lifecycle/asgi.py
mapgraph/lifecycle/base.py
mapgraph/lifecycle/instance.py
mapgraph/statv/__init__.py
mapgraph/typing.py
mapgraph-0.2.9.dist-info/RECORD
