Metadata-Version: 2.1
Name: mapgraph
Version: 0.2.9
Summary: 一个强大的对象控制工具, 覆盖了配置管理、状态管理、上下文管理和生命周期管理。
Author-Email: luxuncang <luxuncang@qq.com>
License: MIT
Requires-Python: >=3.10
Requires-Dist: python-dotenv>=1.0.1
Requires-Dist: typing-tool>=0.1.2
Requires-Dist: networkx>=3.4.2
Requires-Dist: pyyaml>=6.0.2
Requires-Dist: statv>=0.3.2
Provides-Extra: aiohttp
Requires-Dist: aiohttp>=3.10.5; extra == "aiohttp"
Provides-Extra: httpx
Requires-Dist: httpx>=0.27.2; extra == "httpx"
Provides-Extra: uvicorn
Requires-Dist: uvicorn>=0.30.6; extra == "uvicorn"
Provides-Extra: starlette
Requires-Dist: starlette>=0.38.4; extra == "starlette"
